cal_demo/__init__.py
cal_demo/server.py
cal_demo-0.2.0.dist-info/METADATA
cal_demo-0.2.0.dist-info/WHEEL
cal_demo-0.2.0.dist-info/entry_points.txt
cal_demo-0.2.0.dist-info/RECORD
