Metadata-Version: 2.4
Name: cal-demo
Version: 0.2.0
Summary: Add your description here
Author-email: wangjunbin <wangjunbin@zhongan.com>
Requires-Python: >=3.13
Requires-Dist: mcp[cli]>=1.10.1
Requires-Dist: requests>=2.32.4
